jupyter_dcv_proxy/__init__.py
jupyter_dcv_proxy/_version.py
jupyter_dcv_proxy/run-dcv-user-session.sh
jupyter_dcv_proxy/icons/dcv.svg
jupyter_dcv_proxy-3.0.5.dist-info/LICENSE
jupyter_dcv_proxy-3.0.5.dist-info/METADATA
jupyter_dcv_proxy-3.0.5.dist-info/WHEEL
jupyter_dcv_proxy-3.0.5.dist-info/entry_points.txt
jupyter_dcv_proxy-3.0.5.dist-info/top_level.txt
jupyter_dcv_proxy-3.0.5.dist-info/RECORD
