Metadata-Version: 2.1
Name: jupyter-dcv-proxy
Version: 3.0.5
Summary: Jupyter proxy extension to proxy a NICE DCV application.
Home-page: https://github.com/dabble-of-devops-bioanalyze/jupyter-dcv-proxy
Author: Jillian Rowe
Author-email: jillian@dabbleofdevops.com
License: Apache Software License 2.0
Keywords: jupyter_dcv_proxy
Classifier: Development Status :: 2 - Pre-Alpha
Classifier: Intended Audience :: Developers
Classifier: License :: OSI Approved :: Apache Software License
Classifier: Natural Language :: English
Classifier: Programming Language :: Python :: 3
Classifier: Programming Language :: Python :: 3.6
Classifier: Programming Language :: Python :: 3.7
Classifier: Programming Language :: Python :: 3.8
Requires-Python: >=3.6
License-File: LICENSE
Requires-Dist: jupyter-server-proxy (>=3.2.0)
